{"bills":[{"id":2,"date_due":"2016-10-22","name":"supermercado","value":"215.55","done":true},{"id":3,"date_due":"2016-11-31","name":"cart\u00e3o","value":"1256.55","done":false},{"date_due":"10\/10\/2016","name":"combustivel","value":"50.00","done":false,"id":4},{"date_due":"2016-10-10","name":"conta de Telefone","value":"23.56","done":false,"id":5},{"date_due":"2016-09-23","name":"seguro de vida","value":"25.99","done":true,"id":6},{"date_due":"2016-09-08","name":"conta de agua","value":21,"done":false,"id":7},{"date_due":"2016-12-31","name":"das","value":32,"done":false,"id":8}]}